pyfractions/__init__.py
pyfractions/pyfractions.py
pyfractions-0.1.0.dist-info/LICENSE
pyfractions-0.1.0.dist-info/METADATA
pyfractions-0.1.0.dist-info/WHEEL
pyfractions-0.1.0.dist-info/top_level.txt
pyfractions-0.1.0.dist-info/RECORD
