Metadata-Version: 2.1
Name: pyfractions
Version: 0.1.0
Summary: A Python library for working with fractions
Home-page: https://github.com/coderatul/fraction
Author: Atul kushwaha
Author-email: atulkushwaha2008@gmail.com
License: MIT
Project-URL: Source, https://github.com/coderatul/fraction
Project-URL: Tracker, https://github.com/coderatul/fraction/issues
Keywords: fraction math
Classifier: Intended Audience :: Developers
Classifier: License :: OSI Approved :: MIT License
License-File: LICENSE
